{
    "version": 1,
    "license": "CC-BY-SA-3.0",
    "copyright": "sprites taken from https://github.com/cmss13-devs/cmss13/blob/884ab172389b6fc54ef063f5fbea5e8b0a0a2235/icons/mob/humans/underwear.dmi and https://github.com/cmss13-devs/cmss13/blob/884ab172389b6fc54ef063f5fbea5e8b0a0a2235/icons/mob/humans/undershirt.dmi, edited by Huaqas (Github)",
    "size": {
      "x": 32,
      "y": 32
    },
    "states": [
      {
        "name": "briefs_cervidae",
        "directions": 4
      },
      {
        "name": "satin_cervidae",
        "directions": 4
      },
      {
        "name": "boxers_cervidae",
        "directions": 4
      },
      {
        "name": "classic_cervidae",
        "directions": 4
      },
      {
        "name": "sports_cervidae",
        "directions": 4
      },
      {
        "name": "binder_cervidae",
        "directions": 4
      },
      {
        "name": "tanktop_cervidae",
        "directions": 4
      }
    ]
}
